Twper/Twper.py
Twper/__init__.py
Twper-0.1.3.dist-info/DESCRIPTION.rst
Twper-0.1.3.dist-info/METADATA
Twper-0.1.3.dist-info/RECORD
Twper-0.1.3.dist-info/WHEEL
Twper-0.1.3.dist-info/metadata.json
Twper-0.1.3.dist-info/top_level.txt
