Metadata-Version: 2.0
Name: Twper
Version: 0.1.3
Summary: An asynchronous twitter scraper
Home-page: https://github.com/jungerm2/Twper
Author: Sacha Jungerman
Author-email: jungerm2@illinois.edu
License: UNKNOWN
Keywords: twitter scraper async asynchronous fast non-blocking asyncio
Platform: UNKNOWN
Classifier: Development Status :: 3 - Alpha
Classifier: Intended Audience :: Developers
Classifier: Intended Audience :: Science/Research
Classifier: Topic :: Software Development
Classifier: Topic :: Scientific/Engineering
Classifier: Topic :: Software Development :: Libraries :: Python Modules
Classifier: License :: OSI Approved :: MIT License
Classifier: Operating System :: OS Independent
Classifier: Programming Language :: Python :: 3.6
Requires-Dist: coala-utils (~=0.5.0)
Requires-Dist: bs4
Requires-Dist: lxml
Requires-Dist: fake-useragent
Requires-Dist: requests
Requires-Dist: asyncio
Requires-Dist: aiohttp
Requires-Dist: aiostream
